[
    {
        "name": "INFO 340",
        "Introduction": "",
        "Quarter": "",
        "Professor": ""
    },
    {
        "name": "INFO 330",
        "Introduction": "",
        "Quarter": "",
        "Professor": ""
    },
    {
        "name": "INFO 330",
        "Introduction": "",
        "Quarter": "",
        "Professor": ""
    },
    {
        "name": "INFO 330",
        "Introduction": "",
        "Quarter": "",
        "Professor": ""
    },
    {
        "name": "INFO 330",
        "Introduction": "",
        "Quarter": "",
        "Professor": ""
    }
]